ditidy/__init__.py
ditidy/__main__.py
ditidy/cli.py
ditidy/config.py
ditidy/error.py
ditidy/util.py
ditidy/checks/__init__.py
ditidy/checks/checks.py
ditidy/checks/clang_format.py
ditidy/checks/dir_name.py
ditidy/checks/extern_c.py
ditidy/checks/file_name.py
ditidy/checks/git_utils.py
ditidy/checks/include_guard.py
ditidy/checks/shellcheck.py
ditidy/scripts/git_check_ignore.sh
ditidy-2.1.0.dist-info/METADATA
ditidy-2.1.0.dist-info/WHEEL
ditidy-2.1.0.dist-info/entry_points.txt
ditidy-2.1.0.dist-info/licenses/LICENSE
ditidy-2.1.0.dist-info/RECORD
